CHANGES.rst
LICENSE
MANIFEST.in
README.md
setup.py
django_mobile_app_distribution/__init__.py
django_mobile_app_distribution/admin.py
django_mobile_app_distribution/auth_urls.py
django_mobile_app_distribution/exceptions.py
django_mobile_app_distribution/forms.py
django_mobile_app_distribution/models.py
django_mobile_app_distribution/settings.py
django_mobile_app_distribution/storage.py
django_mobile_app_distribution/tests.py
django_mobile_app_distribution/urls.py
django_mobile_app_distribution/views.py
django_mobile_app_distribution.egg-info/PKG-INFO
django_mobile_app_distribution.egg-info/SOURCES.txt
django_mobile_app_distribution.egg-info/dependency_links.txt
django_mobile_app_distribution.egg-info/not-zip-safe
django_mobile_app_distribution.egg-info/requires.txt
django_mobile_app_distribution.egg-info/top_level.txt
django_mobile_app_distribution/locale/de/.DS_Store
django_mobile_app_distribution/locale/de/LC_MESSAGES/.DS_Store
django_mobile_app_distribution/locale/de/LC_MESSAGES/django.mo
django_mobile_app_distribution/locale/de/LC_MESSAGES/django.po
django_mobile_app_distribution/locale/en/LC_MESSAGES/django.mo
django_mobile_app_distribution/locale/en/LC_MESSAGES/django.po
django_mobile_app_distribution/locale/ja/LC_MESSAGES/django.mo
django_mobile_app_distribution/locale/ja/LC_MESSAGES/django.po
django_mobile_app_distribution/migrations/0001_initial.py
django_mobile_app_distribution/migrations/0002_auto_20150730_1357.py
django_mobile_app_distribution/migrations/0003_auto_20150807_1250.py
django_mobile_app_distribution/migrations/0004_auto_20150921_0813.py
django_mobile_app_distribution/migrations/0005_auto_20160118_1759.py
django_mobile_app_distribution/migrations/0006_auto_20160408_1701.py
django_mobile_app_distribution/migrations/__init__.py
django_mobile_app_distribution/static/.DS_Store
django_mobile_app_distribution/static/django_mobile_app_distribution/.DS_Store
django_mobile_app_distribution/static/django_mobile_app_distribution/css/app.css
django_mobile_app_distribution/static/django_mobile_app_distribution/css/app_list.css
django_mobile_app_distribution/static/django_mobile_app_distribution/css/app_list.css.map
django_mobile_app_distribution/static/django_mobile_app_distribution/css/app_list.sass
