Metadata-Version: 1.1
Name: django-mobile-app-distribution
Version: 0.5
Summary: A Django app that adds iOS and Android app upload functionality to the Django admin interface.  Provides a mobile optimized HTML fronted for clients to download Ad Hoc mobile applications using their iOS or Android devices.
Home-page: https://github.com/Proper-Job/django-mobile-app-distribution
Author: Moritz Pfeiffer
Author-email: moritz.pfeiffer@alp-phone.ch
License: MIT License
Platform: UNKNOWN
Classifier: Development Status :: 5 - Production/Stable
Classifier: Environment :: Web Environment
Classifier: Framework :: Django
Classifier: Intended Audience :: Developers
Classifier: License :: OSI Approved :: MIT License
Classifier: Operating System :: OS Independent
Classifier: Programming Language :: Python
Classifier: Programming Language :: Python :: 2.7
Classifier: Programming Language :: Python :: 3.4
Classifier: Programming Language :: Python :: 3.5
Classifier: Topic :: Internet :: WWW/HTTP
Classifier: Topic :: Internet :: WWW/HTTP :: Dynamic Content
